morphinder/__init__.py
morphinder/conf.py
morphinder/morphinder.py
morphinder-0.0.2.dist-info/LICENSE
morphinder-0.0.2.dist-info/METADATA
morphinder-0.0.2.dist-info/WHEEL
morphinder-0.0.2.dist-info/top_level.txt
morphinder-0.0.2.dist-info/RECORD
